Metadata-Version: 1.0
Name: trend-and-season-jm
Version: 0.1
Summary: linear regression with seasonality
Home-page: UNKNOWN
Author: Jason Merwin
Author-email: merwijas@yahoo.com
License: UNKNOWN
Platform: UNKNOWN
